m61/__init__.py
m61/client.py
m61/common.py
m61/exceptions.py
m61/server.py
m61-0.1.0.dist-info/METADATA
m61-0.1.0.dist-info/WHEEL
m61-0.1.0.dist-info/entry_points.txt
m61-0.1.0.dist-info/RECORD
