Metadata-Version: 2.3
Name: m61
Version: 0.1.0
Summary: The name M61 comes from Vulcan, the English name of Vulcanus, the Roman god of fire and blacksmithing. We chose this name to symbolize the massive flow of traffic handled by the project.
Author: andrew.chang(장진우)/kep
Author-email: andrew.chang@kakaoenterprise.com
Requires-Python: >=3.11
Classifier: Programming Language :: Python :: 3
Classifier: Programming Language :: Python :: 3.11
Classifier: Programming Language :: Python :: 3.12
Classifier: Programming Language :: Python :: 3.13
Requires-Dist: psutil (>=7.1.0,<8.0.0)
Requires-Dist: typer[all] (>=0.12.3)
Requires-Dist: typing-extensions (>=4.12.0)
